{
    "url": "https://crowd.xprivacy.eu/?package_name=com.vinwap.parallaxwallpaper", 
    "id": "com.vinwap.parallaxwallpaper", 
    "name": "3D Parallax Background", 
    "versions": {
        "1.14": {
            "url": "https://crowd.xprivacy.eu/?package_name=com.vinwap.parallaxwallpaper&package_version=1.14", 
            "version": "1.14", 
            "stats": {
                "accounts": {
                    "restriction": "accounts", 
                    "used": false, 
                    "methods": {
                        "removeOnAccountsUpdatedListener": {
                            "restriction": "", 
                            "used": false, 
                            "methods": {}, 
                            "restriction_url": "", 
                            "updates": "-", 
                            "cur_allow": 0, 
                            "exception_yes": 0, 
                            "last_update": "2013-09-30 16:44:14", 
                            "ci95": 43.6, 
                            "all_deny": 1, 
                            "all_allow": 0, 
                            "cur_deny": 1, 
                            "method": "removeOnAccountsUpdatedListener", 
                            "exception_no": 1
                        }, 
                        "getAuthToken": {
                            "restriction": "", 
                            "used": false, 
                            "methods": {}, 
                            "restriction_url": "", 
                            "updates": "-", 
                            "cur_allow": 0, 
                            "exception_yes": 0, 
                            "last_update": "2013-09-30 16:43:45", 
                            "ci95": 43.6, 
                            "all_deny": 1, 
                            "all_allow": 0, 
                            "cur_deny": 1, 
                            "method": "getAuthToken", 
                            "exception_no": 1
                        }, 
                        "getAccounts": {
                            "restriction": "", 
                            "used": false, 
                            "methods": {}, 
                            "restriction_url": "", 
                            "updates": "-", 
                            "cur_allow": 0, 
                            "exception_yes": 0, 
                            "last_update": "2013-09-30 16:43:36", 
                            "ci95": 43.6, 
                            "all_deny": 1, 
                            "all_allow": 0, 
                            "cur_deny": 1, 
                            "method": "getAccounts", 
                            "exception_no": 1
                        }, 
                        "hasFeatures": {
                            "restriction": "", 
                            "used": false, 
                            "methods": {}, 
                            "restriction_url": "", 
                            "updates": "-", 
                            "cur_allow": 0, 
                            "exception_yes": 0, 
                            "last_update": "2013-09-30 16:44:08", 
                            "ci95": 43.6, 
                            "all_deny": 1, 
                            "all_allow": 0, 
                            "cur_deny": 1, 
                            "method": "hasFeatures", 
                            "exception_no": 1
                        }, 
                        "getTokenGoogle": {
                            "restriction": "", 
                            "used": false, 
                            "methods": {}, 
                            "restriction_url": "", 
                            "updates": "-", 
                            "cur_allow": 0, 
                            "exception_yes": 0, 
                            "last_update": "2013-09-30 16:43:58", 
                            "ci95": 43.6, 
                            "all_deny": 1, 
                            "all_allow": 0, 
                            "cur_deny": 1, 
                            "method": "getTokenGoogle", 
                            "exception_no": 1
                        }, 
                        "getAuthTokenByFeatures": {
                            "restriction": "", 
                            "used": false, 
                            "methods": {}, 
                            "restriction_url": "", 
                            "updates": "-", 
                            "cur_allow": 0, 
                            "exception_yes": 0, 
                            "last_update": "2013-09-30 16:43:52", 
                            "ci95": 43.6, 
                            "all_deny": 1, 
                            "all_allow": 0, 
                            "cur_deny": 1, 
                            "method": "getAuthTokenByFeatures", 
                            "exception_no": 1
                        }, 
                        "getTokenWithNotificationGoogle": {
                            "restriction": "", 
                            "used": false, 
                            "methods": {}, 
                            "restriction_url": "", 
                            "updates": "-", 
                            "cur_allow": 0, 
                            "exception_yes": 0, 
                            "last_update": "2013-09-30 16:44:00", 
                            "ci95": 43.6, 
                            "all_deny": 1, 
                            "all_allow": 0, 
                            "cur_deny": 1, 
                            "method": "getTokenWithNotificationGoogle", 
                            "exception_no": 1
                        }, 
                        "blockingGetAuthToken": {
                            "restriction": "", 
                            "used": false, 
                            "methods": {}, 
                            "restriction_url": "", 
                            "updates": "-", 
                            "cur_allow": 0, 
                            "exception_yes": 0, 
                            "last_update": "2013-09-30 16:43:28", 
                            "ci95": 43.6, 
                            "all_deny": 1, 
                            "all_allow": 0, 
                            "cur_deny": 1, 
                            "method": "blockingGetAuthToken", 
                            "exception_no": 1
                        }, 
                        "getAccountsByType": {
                            "restriction": "", 
                            "used": false, 
                            "methods": {}, 
                            "restriction_url": "", 
                            "updates": "-", 
                            "cur_allow": 0, 
                            "exception_yes": 0, 
                            "last_update": "2013-09-30 16:43:42", 
                            "ci95": 43.6, 
                            "all_deny": 1, 
                            "all_allow": 0, 
                            "cur_deny": 1, 
                            "method": "getAccountsByType", 
                            "exception_no": 1
                        }, 
                        "getAccountsByTypeAndFeatures": {
                            "restriction": "", 
                            "used": false, 
                            "methods": {}, 
                            "restriction_url": "", 
                            "updates": "-", 
                            "cur_allow": 0, 
                            "exception_yes": 0, 
                            "last_update": "2013-09-30 16:43:44", 
                            "ci95": 43.6, 
                            "all_deny": 1, 
                            "all_allow": 0, 
                            "cur_deny": 1, 
                            "method": "getAccountsByTypeAndFeatures", 
                            "exception_no": 1
                        }, 
                        "addOnAccountsUpdatedListener": {
                            "restriction": "", 
                            "used": false, 
                            "methods": {}, 
                            "restriction_url": "", 
                            "updates": "-", 
                            "cur_allow": 0, 
                            "exception_yes": 0, 
                            "last_update": "2013-09-30 16:43:27", 
                            "ci95": 43.6, 
                            "all_deny": 1, 
                            "all_allow": 0, 
                            "cur_deny": 1, 
                            "method": "addOnAccountsUpdatedListener", 
                            "exception_no": 1
                        }
                    }, 
                    "restriction_url": "https://github.com/M66B/XPrivacy#accounts", 
                    "updates": "-", 
                    "cur_allow": 0, 
                    "exception_yes": 0, 
                    "last_update": "2013-09-30 16:43:15", 
                    "ci95": 43.6, 
                    "all_deny": 1, 
                    "all_allow": 0, 
                    "cur_deny": 1, 
                    "method": "", 
                    "exception_no": 1
                }, 
                "browser": {
                    "restriction": "browser", 
                    "used": false, 
                    "methods": {}, 
                    "restriction_url": "https://github.com/M66B/XPrivacy#browser", 
                    "updates": "-", 
                    "cur_allow": 0, 
                    "exception_yes": 0, 
                    "last_update": "2013-09-30 16:44:16", 
                    "ci95": 43.6, 
                    "all_deny": 1, 
                    "all_allow": 0, 
                    "cur_deny": 1, 
                    "method": "", 
                    "exception_no": 1
                }
            }
        }
    }
}